lingua/__init__.py
lingua/extract.py
lingua/polint.py
lingua/extractors/__init__.py
lingua/extractors/babel.py
lingua/extractors/compat.py
lingua/extractors/python.py
lingua/extractors/xml.py
lingua/extractors/zcml.py
lingua-4.14.dist-info/METADATA
lingua-4.14.dist-info/WHEEL
lingua-4.14.dist-info/entry_points.txt
lingua-4.14.dist-info/top_level.txt
lingua-4.14.dist-info/zip-safe
lingua-4.14.dist-info/RECORD
