Metadata-Version: 2.1
Name: lingua
Version: 4.14
Summary: Translation toolset
Home-page: https://github.com/wichert/lingua
Author: Wichert Akkerman
Author-email: wichert@wiggy.net
License: BSD
Keywords: translation po gettext Babel
Platform: UNKNOWN
Classifier: Intended Audience :: Developers
Classifier: License :: DFSG approved
Classifier: License :: OSI Approved :: BSD License
Classifier: Operating System :: OS Independent
Classifier: Programming Language :: Python :: 2
Classifier: Programming Language :: Python :: 2.6
Classifier: Programming Language :: Python :: 2.7
Classifier: Programming Language :: Python :: 3
Classifier: Programming Language :: Python :: 3.3
Classifier: Programming Language :: Python :: 3.4
Classifier: Programming Language :: Python :: 3.5
Classifier: Topic :: Software Development :: Libraries :: Python Modules
Requires-Dist: setuptools
Requires-Dist: polib
Requires-Dist: click
Requires-Dist: ordereddict ; python_version < "3.0"
Requires-Dist: mock ; python_version < "3.3"
Provides-Extra: chameleonextractor
Requires-Dist: Chameleon ; extra == 'chameleonextractor'
Provides-Extra: tests
Requires-Dist: pytest ; extra == 'tests'
